pltr/__init__.py
pltr/__main__.py
pltr/cli.py
pltr/auth/__init__.py
pltr/auth/base.py
pltr/auth/manager.py
pltr/auth/oauth.py
pltr/auth/storage.py
pltr/auth/token.py
pltr/commands/__init__.py
pltr/commands/admin.py
pltr/commands/alias.py
pltr/commands/completion.py
pltr/commands/configure.py
pltr/commands/connectivity.py
pltr/commands/dataset.py
pltr/commands/folder.py
pltr/commands/mediasets.py
pltr/commands/ontology.py
pltr/commands/orchestration.py
pltr/commands/project.py
pltr/commands/resource.py
pltr/commands/resource_role.py
pltr/commands/shell.py
pltr/commands/space.py
pltr/commands/sql.py
pltr/commands/verify.py
pltr/config/__init__.py
pltr/config/aliases.py
pltr/config/profiles.py
pltr/config/settings.py
pltr/services/__init__.py
pltr/services/admin.py
pltr/services/base.py
pltr/services/connectivity.py
pltr/services/dataset.py
pltr/services/folder.py
pltr/services/mediasets.py
pltr/services/ontology.py
pltr/services/orchestration.py
pltr/services/project.py
pltr/services/resource.py
pltr/services/resource_role.py
pltr/services/space.py
pltr/services/sql.py
pltr/utils/__init__.py
pltr/utils/alias_resolver.py
pltr/utils/completion.py
pltr/utils/formatting.py
pltr/utils/progress.py
pltr_cli-0.11.0.dist-info/METADATA
pltr_cli-0.11.0.dist-info/WHEEL
pltr_cli-0.11.0.dist-info/entry_points.txt
pltr_cli-0.11.0.dist-info/licenses/LICENSE
pltr_cli-0.11.0.dist-info/RECORD
