Metadata-Version: 2.4
Name: pltr-cli
Version: 0.11.0
Summary: Command-line interface for Palantir Foundry APIs
Project-URL: Homepage, https://github.com/anjor/pltr-cli
Project-URL: Repository, https://github.com/anjor/pltr-cli
Project-URL: Issues, https://github.com/anjor/pltr-cli/issues
Project-URL: Changelog, https://github.com/anjor/pltr-cli/blob/main/CHANGELOG.md
Project-URL: Documentation, https://github.com/anjor/pltr-cli/blob/main/README.md
Author-email: anjor <anjor@umd.edu>
License: MIT
License-File: LICENSE
Keywords: api,cli,data,foundry,ontology,palantir
Classifier: Development Status :: 3 - Alpha
Classifier: Environment :: Console
Classifier: Intended Audience :: Developers
Classifier: Intended Audience :: System Administrators
Classifier: License :: OSI Approved :: MIT License
Classifier: Operating System :: OS Independent
Classifier: Programming Language :: Python :: 3
Classifier: Programming Language :: Python :: 3.9
Classifier: Programming Language :: Python :: 3.10
Classifier: Programming Language :: Python :: 3.11
Classifier: Programming Language :: Python :: 3.12
Classifier: Topic :: Software Development :: Libraries :: Python Modules
Classifier: Topic :: System :: Systems Administration
Classifier: Topic :: Utilities
Requires-Python: >=3.9
Requires-Dist: click-repl>=0.3.0
Requires-Dist: foundry-platform-sdk>=1.27.0
Requires-Dist: keyring>=25.6.0
Requires-Dist: python-dotenv>=1.1.1
Requires-Dist: requests>=2.32.4
Requires-Dist: rich>=14.1.0
Requires-Dist: typer>=0.16.0
